pyloxone_api/__init__.py
pyloxone_api/__main__.py
pyloxone_api/api.py
pyloxone_api/const.py
pyloxone_api/discover.py
pyloxone_api/every.py
pyloxone_api/exceptions.py
pyloxone_api/loxtoken.py
pyloxone_api/message.py
pyloxone_api/websocket.py
pyloxone_api-0.2.4.dist-info/LICENSE
pyloxone_api-0.2.4.dist-info/WHEEL
pyloxone_api-0.2.4.dist-info/METADATA
pyloxone_api-0.2.4.dist-info/RECORD
